Metadata-Version: 2.1
Name: fluxt
Version: 0.0.dev2
Summary: A python native stateful streaming framework
Home-page: https://github.com/SamuelHornsey/fluxt
Author: Samuel Hornsey
Author-email: hello@samuelhornsey.com
License: MIT
Project-URL: Bug Reports, https://github.com/SamuelHornsey/fluxt/issues
Project-URL: Repository, https://github.com/SamuelHornsey/fluxt
Keywords: streaming events processing
Requires-Python: >=3.7
Provides-Extra: test
License-File: LICENSE
